dmiapi/DmiApiClient.py
dmiapi/__init__.py
dmiapi/constants.py
dmiapi-0.1.2.dist-info/LICENSE
dmiapi-0.1.2.dist-info/METADATA
dmiapi-0.1.2.dist-info/WHEEL
dmiapi-0.1.2.dist-info/top_level.txt
dmiapi-0.1.2.dist-info/RECORD
