Metadata-Version: 2.1
Name: dmiapi
Version: 0.1.2
Summary: Wrapper for access weather observations and forecasts from the Danish Metrology Institute (DMI) API
Home-page: https://github.com/niklascp/py-dmiapi
Author: Niklas Christoffer Petersen
Author-email: nikalscp@gmail.com
License: MIT
Download-URL: https://github.com/niklascp/py-dmiapi/archive/v0.1.0.tar.gz
Keywords: weather,metrology,forecast,dmi
Platform: UNKNOWN
Classifier: Development Status :: 4 - Beta
Classifier: Intended Audience :: Developers
Classifier: License :: OSI Approved :: MIT License
Requires-Dist: aiohttp
